{"title":"Y los fariseos","slug":"letra-los-fariseos-los-aguilas","author":"Desconocido","album":"Los Águilas","lyrics":"Sólo una cosa sé\n\nQue habiendo sido un ciego\n\nAhora veo la luz de mi Jesús,\n\nLa luz divina que me dio Jesús\n\nCuando por la fe yo vine al Salvador.\n\n\n\nY los fariseos decían sin cesar\n\n//Ese hombre es pecador//.\n\n\n\nSi es pecador yo no lo sé\n\nLo único que sé\n\nEs que Él me salvó.","lyricsStanzas":["Sólo una cosa sé\n\nQue habiendo sido un ciego\n\nAhora veo la luz de mi Jesús,\n\nLa luz divina que me dio Jesús\n\nCuando por la fe yo vine al Salvador.","Y los fariseos decían sin cesar\n\n//Ese hombre es pecador//.","Si es pecador yo no lo sé\n\nLo único que sé\n\nEs que Él me salvó."]}