{"title":"Dios de esta ciudad","slug":"letra-dios-de-esta-ciudad-conquistando-fronteras","author":"Conquistando Fronteras, Andrew Mccan, Peter Comfort, Peter Kernaghan, Richard Bleakley, Aaron Boyd, Ian Jordan","album":"Sube Más Alto","lyrics":"Tú eres rey de este pueblo,\n\nEres Dios en esta ciudad,\n\nEl Señor de esta nación,\n\nEres Dios.\n\n\n\nEres nuestra esperanza,\n\nEres luz en la oscuridad,\n\nEres paz al cansado,\n\nEres Dios.\n\n\n\n//No hay otro como tú//.\n\n\n\n//Grandes cosas vienen ya,\n\nGrandes cosas Dios hará en este pueblo//.","lyricsStanzas":["Tú eres rey de este pueblo,\n\nEres Dios en esta ciudad,\n\nEl Señor de esta nación,\n\nEres Dios.","Eres nuestra esperanza,\n\nEres luz en la oscuridad,\n\nEres paz al cansado,\n\nEres Dios.","//No hay otro como tú//.","//Grandes cosas vienen ya,\n\nGrandes cosas Dios hará en este pueblo//."]}