{"title":"Búscale","slug":"letra-buscale-alabanzas-y-canticos-de-adoracion","author":"Desconocido","album":"Alabanzas y Canticos de Adoración, Vol. 1","lyrics":"Si Jesús viniera hoy\nQue cuentas le irías a dar\nSi viniera hoy por su pueblo\n\n\n\n\n\n\nBúscale, búscale ahora que hay tiempo \nNo desperdicies tu tiempo \nQue mañana tarde será \n\nBúscale, te aseguro que te irá muy bien \n\nSi le buscas hoy cuenta te darás \n\nDe que se vive mas seguro con él \n\nII\nBúscale, búscale ahora que hay tiempo\nNo desperdicies tu tiempo\nQue mañana tarde será\n\n\n\n\nDime que es lo que te detiene \nPara entregar tu vida a él \nLo que sea él lo entiende \n\nPorque él vino y fue humano también\nDime que es lo que te detiene\nPara entregar tu vida a él\nLo que sea él lo entiende","lyricsStanzas":["Si Jesús viniera hoy\nQue cuentas le irías a dar\nSi viniera hoy por su pueblo\n\n\n\n\n\n\nBúscale, búscale ahora que hay tiempo \nNo desperdicies tu tiempo \nQue mañana tarde será \n\nBúscale, te aseguro que te irá muy bien \n\nSi le buscas hoy cuenta te darás \n\nDe que se vive mas seguro con él \n\nII\nBúscale, búscale ahora que hay tiempo\nNo desperdicies tu tiempo\nQue mañana tarde será\n\n\n\n\nDime que es lo que te detiene \nPara entregar tu vida a él \nLo que sea él lo entiende \n\nPorque él vino y fue humano también\nDime que es lo que te detiene\nPara entregar tu vida a él\nLo que sea él lo entiende"]}