{"title":"Como el siervo busca por las aguas","slug":"letra-llename-de-ti-marcos-witt","author":"Marcos Witt","album":"Tu y Yo (Remasterizado)","lyrics":"Como el siervo\n\nBusca por las aguas\n\nAsí clama mi alma\n\nPor ti Señor\n\nDía y noche\n\nYo tengo sed de ti\n\nY solo a ti buscaré.\n\n\n\n//Lléname// Señor\n\nDame más, más de tu amor\n\nYo tengo sed\n\nSolo de ti\n\nLléname Señor.","lyricsStanzas":["Como el siervo\n\nBusca por las aguas\n\nAsí clama mi alma\n\nPor ti Señor\n\nDía y noche\n\nYo tengo sed de ti\n\nY solo a ti buscaré.","//Lléname// Señor\n\nDame más, más de tu amor\n\nYo tengo sed\n\nSolo de ti\n\nLléname Señor."]}