{"title":"Yo sigo aquí","slug":"letra-sigo-aqui-david-guzman","author":"David Guzman","album":"Mi Primera Década","lyrics":"Y yo sigo aquí\nesperando de tu bendición\nY yo sigo aquí\na pesar de las dificultades\nY yo sigo aquí\nen el mismo camino\nQue me lleva\nal cielo mi Jesús\nOh yo quiero\nsaber si hay espacio para mas\nY una voz me\ndice para todo el que quiera entrar\nMi vida di por\nti, mi sangre derramé por amarte a ti\n\nCoro\nAunque el\nmundo me ilusione con sus cosas raras\nYo quiero\ndemostrarles a todos que yo sigo aquí, aleluya\nGuiado siempre\nen el poder de su Santo Espíritu\nPor eso y por\nmuchas razones yo sigo aquí\n\nYo no entiendo\ncomo hay muchos que se apartan de ti\nApenas les\npica un piojo ya se quieren ir\nLes hace falta\nmás unción para reprender\nAl enemigo que\nbusca la forma de alejarnos de ti","lyricsStanzas":["Y yo sigo aquí\nesperando de tu bendición\nY yo sigo aquí\na pesar de las dificultades\nY yo sigo aquí\nen el mismo camino\nQue me lleva\nal cielo mi Jesús\nOh yo quiero\nsaber si hay espacio para mas\nY una voz me\ndice para todo el que quiera entrar\nMi vida di por\nti, mi sangre derramé por amarte a ti\n\nCoro\nAunque el\nmundo me ilusione con sus cosas raras\nYo quiero\ndemostrarles a todos que yo sigo aquí, aleluya\nGuiado siempre\nen el poder de su Santo Espíritu\nPor eso y por\nmuchas razones yo sigo aquí\n\nYo no entiendo\ncomo hay muchos que se apartan de ti\nApenas les\npica un piojo ya se quieren ir\nLes hace falta\nmás unción para reprender\nAl enemigo que\nbusca la forma de alejarnos de ti"]}