{"title":"Abrázame","slug":"letra-abrazame-wilder-ascanio","author":"Wilder Ascanio","album":"Abrazame","lyrics":"Abrázame señor, yo quiero sentir tu presencia\nAbrázame señor, yo quiero sentir tu calor\n\nAbrázame señor, yo quiero sentir tu calor\nAbrázame porque los vientos quieren tumbar mi casa\n\nAbrázame porque los vientos quieren tumbar mi casa\nLa tormenta se acrecienta y mi refugio eres tu señor\n\nLa tormenta se acrecienta y mi refugio eres tu señor\nAbrázame porque los problemas han llegado a mi vida\n\nAbrázame porque los problemas han llegado a mi vida\nY te aseguro que no sobreviviría mucho tiempo sin ti\n\nY te aseguro que no sobreviviría mucho tiempo sin ti\n\nCoro Coro\nAbrázame señor Jesús, necesito sentir tus manos sobre mí\n\nAbrázame señor Jesús, necesito sentir tus manos sobre mí\nAbrázame, con tus alas ángel de justicia…abrázame\n\nAbrázame, con tus alas ángel de justicia…abrázame\n\nIIII\nCuando el cristiano acostumbra siempre a depender de Dios\n\nCuando el cristiano acostumbra siempre a depender de Dios\nDonde vaya, donde esté, él siempre estará seguro\n\nDonde vaya, donde esté, él siempre estará seguro\nCuando el vestido, el alimento estén acabando\n\nCuando el vestido, el alimento estén acabando\nEl tiene su confianza en el señor, que no lo dejará\n\nEl tiene su confianza en el señor, que no lo dejará\nY dice la palabra de Dios que no deja avergonzado\n\nTodo aquel que pone su confianza plena en el señor","lyricsStanzas":["Abrázame señor, yo quiero sentir tu presencia\nAbrázame señor, yo quiero sentir tu calor\n\nAbrázame señor, yo quiero sentir tu calor\nAbrázame porque los vientos quieren tumbar mi casa\n\nAbrázame porque los vientos quieren tumbar mi casa\nLa tormenta se acrecienta y mi refugio eres tu señor\n\nLa tormenta se acrecienta y mi refugio eres tu señor\nAbrázame porque los problemas han llegado a mi vida\n\nAbrázame porque los problemas han llegado a mi vida\nY te aseguro que no sobreviviría mucho tiempo sin ti\n\nY te aseguro que no sobreviviría mucho tiempo sin ti\n\nCoro Coro\nAbrázame señor Jesús, necesito sentir tus manos sobre mí\n\nAbrázame señor Jesús, necesito sentir tus manos sobre mí\nAbrázame, con tus alas ángel de justicia…abrázame\n\nAbrázame, con tus alas ángel de justicia…abrázame\n\nIIII\nCuando el cristiano acostumbra siempre a depender de Dios\n\nCuando el cristiano acostumbra siempre a depender de Dios\nDonde vaya, donde esté, él siempre estará seguro\n\nDonde vaya, donde esté, él siempre estará seguro\nCuando el vestido, el alimento estén acabando\n\nCuando el vestido, el alimento estén acabando\nEl tiene su confianza en el señor, que no lo dejará\n\nEl tiene su confianza en el señor, que no lo dejará\nY dice la palabra de Dios que no deja avergonzado\n\nTodo aquel que pone su confianza plena en el señor"]}