{"title":"Había un hombrecito chueco","slug":"letra-habia-un-hombrecito-chueco-cancion-cristiana","author":"Desconocido","album":null,"lyrics":"Vivía en una casa chueca\n\nTenía pensamientos chuecos\n\nSu vida toda era chueca.\n\n\n\nUn día el hombrecito chueco\n\nLa Biblia se encontró\n\n//Y todo lo que era chueco\n\nJesús enderezó//.","lyricsStanzas":["Vivía en una casa chueca\n\nTenía pensamientos chuecos\n\nSu vida toda era chueca.","Un día el hombrecito chueco\n\nLa Biblia se encontró\n\n//Y todo lo que era chueco\n\nJesús enderezó//."]}