{"title":"Rendido","slug":"letra-rendido-manantial-de-inspiracion","author":"Manantial de Inspiración","album":null,"lyrics":"Yo quiero estar ante Ti , mi Señor,\nDispuesto a escucharte, sumiso a tu voz,Dispuesto a escucharte, sumiso a tu voz,\nA ir donde quieras, a hacer tu voluntad;A ir donde quieras, a hacer tu voluntad;\nYo quiero ante Ti rendido estar.Yo quiero ante Ti rendido estar.\nCoro\n\nCoro\nRendido, rendido estoy ante Ti,Rendido, rendido estoy ante Ti,\nYo quiero ponerme en tus manos, Señor;Yo quiero ponerme en tus manos, Señor;\nMis manos levanto en adoración:Mis manos levanto en adoración:\nYo quiero rendirme en tus manos, Señor.Yo quiero rendirme en tus manos, Señor.\nIIII\nNada de mí yo te puedo ofrecer:Nada de mí yo te puedo ofrecer:\nVengo ante Ti tal como soy;Vengo ante Ti tal como soy;\nNo encuentro palabras para expresar\n\nNo encuentro palabras para expresar\nLo que es sentirte cerca,Lo que es sentirte cerca,\nY tu voz escuchar.Y tu voz escuchar.","lyricsStanzas":["Yo quiero estar ante Ti , mi Señor,\nDispuesto a escucharte, sumiso a tu voz,Dispuesto a escucharte, sumiso a tu voz,\nA ir donde quieras, a hacer tu voluntad;A ir donde quieras, a hacer tu voluntad;\nYo quiero ante Ti rendido estar.Yo quiero ante Ti rendido estar.\nCoro\n\nCoro\nRendido, rendido estoy ante Ti,Rendido, rendido estoy ante Ti,\nYo quiero ponerme en tus manos, Señor;Yo quiero ponerme en tus manos, Señor;\nMis manos levanto en adoración:Mis manos levanto en adoración:\nYo quiero rendirme en tus manos, Señor.Yo quiero rendirme en tus manos, Señor.\nIIII\nNada de mí yo te puedo ofrecer:Nada de mí yo te puedo ofrecer:\nVengo ante Ti tal como soy;Vengo ante Ti tal como soy;\nNo encuentro palabras para expresar\n\nNo encuentro palabras para expresar\nLo que es sentirte cerca,Lo que es sentirte cerca,\nY tu voz escuchar.Y tu voz escuchar."]}