{"title":"Oveja descarriada","slug":"letra-oveja-descarriada-duo-hermanos-devia","author":"Dúo Hermanos Devia","album":"Lazos de Amor","lyrics":"Se fue en una tarde muy lluviosa\nEl cielo estaba triste y apagado\n\nEl cielo estaba triste y apagado\nLos rayos la asustaron demasiado\n\nLos rayos la asustaron demasiado\nY se fue del redil dispuesta a divagar Y se fue del redil dispuesta a divagar\nEn las oscuras sendas\n\nEn las oscuras sendas\n\nCoro\n\nCoro\n¿Dónde estás oveja descarriada?¿Dónde estás oveja descarriada?\nTu pastor vive por ti llorando Tu pastor vive por ti llorando\nSin cesar te busca día y noche\n\nSin cesar te busca día y noche\nPues teme por tu vida y bienestar\n\nPues teme por tu vida y bienestar\nVuelve aquí, \nno sigas divagando\n\nVuelve aquí, \nno sigas divagando\nEl lobo por allí está rondando\n\nEl lobo por allí está rondando\nInsensata, no expongas más tu vida\n\nInsensata, no expongas más tu vida\nEl pastor te ofrece buenos pastos\n\nEl pastor te ofrece buenos pastos\n\nIIII\nHermano que eres fiel a Jesucristo\n\nHermano que eres fiel a Jesucristo\nNo temas cuando vengan las tormentas\n\nNo temas cuando vengan las tormentas\nSon pruebas que no deben asustarte\n\nSon pruebas que no deben asustarte\nPues Cristo el buen pastor siempre te ayudará\n\nPues Cristo el buen pastor siempre te ayudará\nPara que no desmayes\n\nPara que no desmayes","lyricsStanzas":["Se fue en una tarde muy lluviosa\nEl cielo estaba triste y apagado\n\nEl cielo estaba triste y apagado\nLos rayos la asustaron demasiado\n\nLos rayos la asustaron demasiado\nY se fue del redil dispuesta a divagar Y se fue del redil dispuesta a divagar\nEn las oscuras sendas\n\nEn las oscuras sendas\n\nCoro\n\nCoro\n¿Dónde estás oveja descarriada?¿Dónde estás oveja descarriada?\nTu pastor vive por ti llorando Tu pastor vive por ti llorando\nSin cesar te busca día y noche\n\nSin cesar te busca día y noche\nPues teme por tu vida y bienestar\n\nPues teme por tu vida y bienestar\nVuelve aquí, \nno sigas divagando\n\nVuelve aquí, \nno sigas divagando\nEl lobo por allí está rondando\n\nEl lobo por allí está rondando\nInsensata, no expongas más tu vida\n\nInsensata, no expongas más tu vida\nEl pastor te ofrece buenos pastos\n\nEl pastor te ofrece buenos pastos\n\nIIII\nHermano que eres fiel a Jesucristo\n\nHermano que eres fiel a Jesucristo\nNo temas cuando vengan las tormentas\n\nNo temas cuando vengan las tormentas\nSon pruebas que no deben asustarte\n\nSon pruebas que no deben asustarte\nPues Cristo el buen pastor siempre te ayudará\n\nPues Cristo el buen pastor siempre te ayudará\nPara que no desmayes\n\nPara que no desmayes"]}