{"title":"Santo es el que vive de Montesanto","slug":"letra-santo-es-el-que-vive-montesanto","author":"Montesanto","album":"Fiesta en el Desierto (la la la)","lyrics":"Santo es el que vive, santo es el que reina\n\nSanto en las alturas, santo aquí en la tierra\n\nSanto en el pesebre, santo en el sepulcro\n\nSanta es su sangre derramada en la cruz.\n\n\n\nSanto es el que vive, santo es el que reina\n\nSanto en las alturas, santo aquí en la tierra\n\nSanto en el pesebre, santo en el sepulcro\n\nSanta es su sangre derramada en la cruz.\n\n\n\nCorrió su sangre por el madero\n\nA Él no lo mataron, se entregó primero\n\nDe tal manera amó Jesús\n\nQue entregó su vida en la Cruz.\n\n\n\nNo dijo nada, no abrió su boca\n\nLe hieren, le golpean, pero Él perdona;\n\nDe tal manera amó Jesús\n\nQue entregó su vida en la cruz.\n\n\n\nSanto es el que vive, santo es el que reina\n\nSanto en las alturas, santo aquí en la tierra\n\nSanto en el pesebre, santo en el sepulcro\n\nSanta es su sangre derramada en la cruz.\n\n\n\nSanto es el que vive, santo es el que reina\n\nSanto en las alturas, santo aquí en la tierra\n\nSanto en el pesebre, santo en el sepulcro\n\nSanta es su sangre derramada en la cruz.\n\n\n\nSanto, santo, santo\n\nEl Cordero y León\n\n\n\nTodo ojo verá\n\nToda rodilla se doblará\n\nAnte el Cordero y León\n\n\n\nTodos lo verán, como Rey en las nubes volverá,\n\nCoronado en Poder y Autoridad,\n\nEl Cordero y León reinará.\n\n\n\nTodos lo verán, como Rey en las nubes volverá,\n\nCoronado en Poder y Autoridad,\n\nEl Cordero y León reinará\n\n\n\nTodos lo verán, como Rey en las nubes volverá,\n\nCoronado en Poder y Autoridad,\n\nEl Cordero y León reinará.\n\n\n\nTodos lo verán, como Rey en las nubes volverá,\n\nCoronado en Poder y Autoridad,\n\nEl Cordero y León reinará.\n\n\n\nSanto es el que vive, santo es el que reina\n\nSanto en las alturas, santo aquí en la tierra\n\nSanto en el pesebre, santo en el sepulcro\n\nSanta es su sangre derramada en la cruz.\n\n\n\nSanto es el que vive, santo es el que reina\n\nSanto en las alturas, santo aquí en la tierra\n\nSanto en el pesebre, santo en el sepulcro\n\nSanta es su sangre derramada en la cruz.\n\n\n\nTodos lo verán, como Rey en las nubes volverá,\n\nCoronado en poder y autoridad\n\nEl Cordero y León reinará.\n\n\n\nTodos lo verán, como Rey en las nubes volverá\n\nCoronado en poder y autoridad\n\nEl Cordero y León reinará.\n\n\n\nTodos lo verán, como Rey en las nubes volverá\n\nCoronado en poder y autoridad\n\nEl Cordero y León reinará.\n\n\n\nTodos lo verán, como Rey en las nubes volverá (Él regresará)\n\nCoronado en poder y autoridad (con coronas de autoridad)\n\nEl Cordero y León reinará.\n\n\n\nNos unimos al cántico nuevo, al cántico nuevo\n\nQue se canta en el cielo\n\nY le dice Santo al Cordero.\n\n\n\nNos unimos al cántico nuevo, al cántico del cielo\n\nQue le canta al Cordero\n\nY le dice Santo.\n\n\n\nSanto, santo, santo, santo es Jesús de Nazareth,\n\nSanto, santo, santo, santo es Jesús de Nazareth,\n\nSanto, santo, santo, santo es Jesús de Nazareth,\n\nSanto, santo, santo, santo es Jesús de Nazareth.\n\n\n\nSanto, santo, santo, santo es Jesús de Nazareth,\n\nSanto, santo, santo, santo es Jesús de Nazareth,\n\nSanto, santo, santo, santo es Jesús de Nazareth,\n\nSanto, santo, santo, santo es Jesús de Nazareth.\n\n\n\nSanto, santo, santo, santo es Jesús de Nazareth,\n\nSanto, santo, santo, santo es Jesús de Nazareth,\n\nSanto, santo, santo, santo es Jesús de Nazareth,\n\nSanto, santo, santo, santo es Jesús de Nazareth.\n\n\n\nSanto, santo, santo, santo es Jesús de Nazareth,\n\nSanto, santo, santo, santo es Jesús de Nazareth,\n\nSanto, santo, santo, santo es Jesús de Nazareth,\n\nSanto, santo, santo, santo es Jesús de Nazareth.\n\n\n\nTodos lo verán, como Rey en las nubes volverá\n\nCoronado en poder y autoridad\n\nEl Cordero y León reinará.\n\n\n\nTodos lo verán, como Rey en las nubes volverá\n\nCoronado en poder y autoridad\n\nEl Cordero y León reinará.\n\n\n\nSanto es el que vive, santo es el que reina\n\nSanto en las alturas, santo aquí en la tierra\n\nSanto en el pesebre, santo en el sepulcro\n\nSanta es su sangre derramada en la cruz.\n\n\n\nSanto es el que vive, santo es el que reina\n\nSanto en las alturas, santo aquí en la tierra\n\nSanto en el pesebre, santo en el sepulcro\n\nSanta es su sangre derramada en la cruz.\n\n\n\nAlguien tiene que decirle\n\nAlguien tiene que alabarte\n\nAlguien tiene que exaltarte.\n\n\n\nSanto, santo\n\nAlguien tiene que decirte\n\nSanto, santo, santo, santo\n\nSanto, santo, santo, santo\n\nAlguien tiene que gritar\n\nAlguien tiene que exaltarte.\n\n\n\nSanto, santo, santo, santo\n\nSanto, santo, santo, santo\n\nSanto, santo, santo, santo es Jesús de Nazareth.\n\n\n\nSanto, santo, santo, santo\n\nSanto, santo, santo, santo es Jesús de Nazareth.\n\n\n\nEn el ámbito musical, es fundamental destacar cuándo una banda logra no solo interpretar sino redefinir una obra clásica. GP BAND, la banda musical de Generación Pentecostal, ha hecho precisamente eso con la Letra Santo es el que vive de Montesanto, una pieza cargada de espiritualidad y devoción.\n\n\n\nLa Letra Santo es el que vive de Montesanto es conocida por su profundo mensaje espiritual, abordando temas de santidad, sacrificio y redención. GP BAND, en su última adaptación, ha tomado esta letra y ha impregnado su esencia única, dando vida a una versión que, aunque fiel al original, tiene un toque fresco y contemporáneo.\n\n\n\nLa originalidad de la Letra Santo es el que vive de Montesanto se ve amplificada en el cover de GP BAND. Las líneas que hablan sobre el sacrificio divino y el perdón resuenan con una intensidad particular en su versión. Y es que, en una era donde el contenido se consume rápidamente, el hecho de que una banda decida resaltar y revitalizar una canción tan significativa es digno de mención.\n\n\n\nLa Letra Santo es el que vive de Montesanto ya posee un poder evocador en su forma original, pero con GP BAND se convierte en una experiencia auditiva sin igual, y ha logrado crear una experiencia musical enriquecedora, manteniendo la Letra Santo es el que vive de Montesanto en el centro de su proyecto. Es un tributo, una renovación y, sobre todo, un regalo para todos los amantes de la música cristiana.","lyricsStanzas":["Santo es el que vive, santo es el que reina\n\nSanto en las alturas, santo aquí en la tierra\n\nSanto en el pesebre, santo en el sepulcro\n\nSanta es su sangre derramada en la cruz.","Santo es el que vive, santo es el que reina\n\nSanto en las alturas, santo aquí en la tierra\n\nSanto en el pesebre, santo en el sepulcro\n\nSanta es su sangre derramada en la cruz.","Corrió su sangre por el madero\n\nA Él no lo mataron, se entregó primero\n\nDe tal manera amó Jesús\n\nQue entregó su vida en la Cruz.","No dijo nada, no abrió su boca\n\nLe hieren, le golpean, pero Él perdona;\n\nDe tal manera amó Jesús\n\nQue entregó su vida en la cruz.","Santo es el que vive, santo es el que reina\n\nSanto en las alturas, santo aquí en la tierra\n\nSanto en el pesebre, santo en el sepulcro\n\nSanta es su sangre derramada en la cruz.","Santo es el que vive, santo es el que reina\n\nSanto en las alturas, santo aquí en la tierra\n\nSanto en el pesebre, santo en el sepulcro\n\nSanta es su sangre derramada en la cruz.","Santo, santo, santo\n\nEl Cordero y León","Todo ojo verá\n\nToda rodilla se doblará\n\nAnte el Cordero y León","Todos lo verán, como Rey en las nubes volverá,\n\nCoronado en Poder y Autoridad,\n\nEl Cordero y León reinará.","Todos lo verán, como Rey en las nubes volverá,\n\nCoronado en Poder y Autoridad,\n\nEl Cordero y León reinará","Todos lo verán, como Rey en las nubes volverá,\n\nCoronado en Poder y Autoridad,\n\nEl Cordero y León reinará.","Todos lo verán, como Rey en las nubes volverá,\n\nCoronado en Poder y Autoridad,\n\nEl Cordero y León reinará.","Santo es el que vive, santo es el que reina\n\nSanto en las alturas, santo aquí en la tierra\n\nSanto en el pesebre, santo en el sepulcro\n\nSanta es su sangre derramada en la cruz.","Santo es el que vive, santo es el que reina\n\nSanto en las alturas, santo aquí en la tierra\n\nSanto en el pesebre, santo en el sepulcro\n\nSanta es su sangre derramada en la cruz.","Todos lo verán, como Rey en las nubes volverá,\n\nCoronado en poder y autoridad\n\nEl Cordero y León reinará.","Todos lo verán, como Rey en las nubes volverá\n\nCoronado en poder y autoridad\n\nEl Cordero y León reinará.","Todos lo verán, como Rey en las nubes volverá\n\nCoronado en poder y autoridad\n\nEl Cordero y León reinará.","Todos lo verán, como Rey en las nubes volverá (Él regresará)\n\nCoronado en poder y autoridad (con coronas de autoridad)\n\nEl Cordero y León reinará.","Nos unimos al cántico nuevo, al cántico nuevo\n\nQue se canta en el cielo\n\nY le dice Santo al Cordero.","Nos unimos al cántico nuevo, al cántico del cielo\n\nQue le canta al Cordero\n\nY le dice Santo.","Santo, santo, santo, santo es Jesús de Nazareth,\n\nSanto, santo, santo, santo es Jesús de Nazareth,\n\nSanto, santo, santo, santo es Jesús de Nazareth,\n\nSanto, santo, santo, santo es Jesús de Nazareth.","Santo, santo, santo, santo es Jesús de Nazareth,\n\nSanto, santo, santo, santo es Jesús de Nazareth,\n\nSanto, santo, santo, santo es Jesús de Nazareth,\n\nSanto, santo, santo, santo es Jesús de Nazareth.","Santo, santo, santo, santo es Jesús de Nazareth,\n\nSanto, santo, santo, santo es Jesús de Nazareth,\n\nSanto, santo, santo, santo es Jesús de Nazareth,\n\nSanto, santo, santo, santo es Jesús de Nazareth.","Santo, santo, santo, santo es Jesús de Nazareth,\n\nSanto, santo, santo, santo es Jesús de Nazareth,\n\nSanto, santo, santo, santo es Jesús de Nazareth,\n\nSanto, santo, santo, santo es Jesús de Nazareth.","Todos lo verán, como Rey en las nubes volverá\n\nCoronado en poder y autoridad\n\nEl Cordero y León reinará.","Todos lo verán, como Rey en las nubes volverá\n\nCoronado en poder y autoridad\n\nEl Cordero y León reinará.","Santo es el que vive, santo es el que reina\n\nSanto en las alturas, santo aquí en la tierra\n\nSanto en el pesebre, santo en el sepulcro\n\nSanta es su sangre derramada en la cruz.","Santo es el que vive, santo es el que reina\n\nSanto en las alturas, santo aquí en la tierra\n\nSanto en el pesebre, santo en el sepulcro\n\nSanta es su sangre derramada en la cruz.","Alguien tiene que decirle\n\nAlguien tiene que alabarte\n\nAlguien tiene que exaltarte.","Santo, santo\n\nAlguien tiene que decirte\n\nSanto, santo, santo, santo\n\nSanto, santo, santo, santo\n\nAlguien tiene que gritar\n\nAlguien tiene que exaltarte.","Santo, santo, santo, santo\n\nSanto, santo, santo, santo\n\nSanto, santo, santo, santo es Jesús de Nazareth.","Santo, santo, santo, santo\n\nSanto, santo, santo, santo es Jesús de Nazareth.","En el ámbito musical, es fundamental destacar cuándo una banda logra no solo interpretar sino redefinir una obra clásica. GP BAND, la banda musical de Generación Pentecostal, ha hecho precisamente eso con la Letra Santo es el que vive de Montesanto, una pieza cargada de espiritualidad y devoción.","La Letra Santo es el que vive de Montesanto es conocida por su profundo mensaje espiritual, abordando temas de santidad, sacrificio y redención. GP BAND, en su última adaptación, ha tomado esta letra y ha impregnado su esencia única, dando vida a una versión que, aunque fiel al original, tiene un toque fresco y contemporáneo.","La originalidad de la Letra Santo es el que vive de Montesanto se ve amplificada en el cover de GP BAND. Las líneas que hablan sobre el sacrificio divino y el perdón resuenan con una intensidad particular en su versión. Y es que, en una era donde el contenido se consume rápidamente, el hecho de que una banda decida resaltar y revitalizar una canción tan significativa es digno de mención.","La Letra Santo es el que vive de Montesanto ya posee un poder evocador en su forma original, pero con GP BAND se convierte en una experiencia auditiva sin igual, y ha logrado crear una experiencia musical enriquecedora, manteniendo la Letra Santo es el que vive de Montesanto en el centro de su proyecto. Es un tributo, una renovación y, sobre todo, un regalo para todos los amantes de la música cristiana."]}