{"title":"Jesús tu estas aquí","slug":"letra-jesus-tu-estas-aqui-verbo-y-vida","author":"Verbo y Vida, Solangie Rodriguez, Carlos Andres Vasquez","album":"Esto Es: Verbo y Vida","lyrics":"Jesús tu estas aquí - Carlos Andrés Vasquez\n\nJesús\n\nOtra vez estoy aquí\n\nPara adorarte, Jesucristo\n\nMi corazón te anhela más\n\nQuiero rendirme a tus pies, Señor\n\nPara adorarte, Jesucristo\n\nMi corazón te anhela más\n\nQuiero rendirme a tus pies, Señor\nJesús tu estas aquí - Carlos Andrés Vasquez\n\nJesús\nOtra vez estoy aquí\n\n\n\nEstoy sintiendo tu espíritu en mí\n\nSiento correr la unción aquí\n\nMe está tocando tu fuego celestial\n\nEn tu presencia yo quiero adorar\n\nSiento correr la unción aquí\n\nMe está tocando tu fuego celestial\n\nEn tu presencia yo quiero adorar\nEstoy sintiendo tu espíritu en mí\n\n\n\nJesús tú estás aquí\n\nSiento que me lleno de ti\n\nNo quiero parar de adorar\n\nPues me das libertad\n\nJesús tú estás aquí\n\nSiento que me lleno de ti\n\nNo quiero parar de adorar\n\nPues me das libertad\n\nSiento que me lleno de ti\n\nNo quiero parar de adorar\n\nPues me das libertad\n\nJesús tú estás aquí\n\nSiento que me lleno de ti\n\nNo quiero parar de adorar\n\nPues me das libertad\nJesús tú estás aquí\n\n\n\n\n\n\n\nOtra vez estoy aquí\n\nPara adorarte, Jesucristo\n\nMi corazón te anhela más\n\nQuiero rendirme a tus pies, Señor\n\nPara adorarte, Jesucristo\n\nMi corazón te anhela más\n\nQuiero rendirme a tus pies, Señor\nOtra vez estoy aquí\n\n\n\nEstoy sintiendo tu espíritu en mí\n\nSiento correr la unción aquí\n\nMe está tocando tu fuego celestial\n\nY en tu presencia yo quiero adorar\n\nSiento correr la unción aquí\n\nMe está tocando tu fuego celestial\n\nY en tu presencia yo quiero adorar\nEstoy sintiendo tu espíritu en mí\n\n\n\nJesús tú estás aquí\n\nSiento que me lleno de ti\n\nNo quiero parar de adorar\n\nPues me das libertad\n\nJesús tú estás aquí\n\nSiento que me lleno de ti\n\nNo quiero parar de adorar\n\nPues me das libertad\n\nSiento que me lleno de ti\n\nNo quiero parar de adorar\n\nPues me das libertad\n\nJesús tú estás aquí\n\nSiento que me lleno de ti\n\nNo quiero parar de adorar\n\nPues me das libertad\nJesús tú estás aquí\n\n\n\n\n\n\n\nUuoouh, uuoouh, uh, uh, uuuh\n\nUuoouh, uuoouh, uh, uh, uuuh\n\nUuoouh, uuoouh, uh, uh, uuuh\nUuoouh, uuoouh, uh, uh, uuuh\nUuoouh, uuoouh, uh, uh, uuuh\nEstoy sintiendo tu espíritu en mí\n\nSiento correr la unción aquí\n\nMe está tocando tu fuego celestial\n\nY en tu presencia yo quiero adorar\n\nSiento correr la unción aquí\n\nMe está tocando tu fuego celestial\n\nY en tu presencia yo quiero adorar\nEstoy sintiendo tu espíritu en mí\n\n\n\nJesús tú estás aquí\n\nSiento que me lleno de ti\n\nNo quiero parar de adorar\n\nPues me das libertad\n\nJesús tú estás aquí\n\nSiento que me lleno de ti\n\nNo quiero parar de adorar\n\nPues me das libertad\n\nSiento que me lleno de ti\n\nNo quiero parar de adorar\n\nPues me das libertad\n\nJesús tú estás aquí\n\nSiento que me lleno de ti\n\nNo quiero parar de adorar\n\nPues me das libertad\nJesús tú estás aquí\n\n\n\n\n\n\n\nPues me das libertad\n\nPues me das libertad\n\nPues me das libertad\n\n\n\nPues me das libertad\n\nPues me das libertad\n\n\nPues me das libertad","lyricsStanzas":["Jesús tu estas aquí - Carlos Andrés Vasquez\n\nJesús\n\nOtra vez estoy aquí\n\nPara adorarte, Jesucristo\n\nMi corazón te anhela más\n\nQuiero rendirme a tus pies, Señor\n\nPara adorarte, Jesucristo\n\nMi corazón te anhela más\n\nQuiero rendirme a tus pies, Señor\nJesús tu estas aquí - Carlos Andrés Vasquez\n\nJesús\nOtra vez estoy aquí\n\n\n\nEstoy sintiendo tu espíritu en mí\n\nSiento correr la unción aquí\n\nMe está tocando tu fuego celestial\n\nEn tu presencia yo quiero adorar\n\nSiento correr la unción aquí\n\nMe está tocando tu fuego celestial\n\nEn tu presencia yo quiero adorar\nEstoy sintiendo tu espíritu en mí\n\n\n\nJesús tú estás aquí\n\nSiento que me lleno de ti\n\nNo quiero parar de adorar\n\nPues me das libertad\n\nJesús tú estás aquí\n\nSiento que me lleno de ti\n\nNo quiero parar de adorar\n\nPues me das libertad\n\nSiento que me lleno de ti\n\nNo quiero parar de adorar\n\nPues me das libertad\n\nJesús tú estás aquí\n\nSiento que me lleno de ti\n\nNo quiero parar de adorar\n\nPues me das libertad\nJesús tú estás aquí\n\n\n\n\n\n\n\nOtra vez estoy aquí\n\nPara adorarte, Jesucristo\n\nMi corazón te anhela más\n\nQuiero rendirme a tus pies, Señor\n\nPara adorarte, Jesucristo\n\nMi corazón te anhela más\n\nQuiero rendirme a tus pies, Señor\nOtra vez estoy aquí\n\n\n\nEstoy sintiendo tu espíritu en mí\n\nSiento correr la unción aquí\n\nMe está tocando tu fuego celestial\n\nY en tu presencia yo quiero adorar\n\nSiento correr la unción aquí\n\nMe está tocando tu fuego celestial\n\nY en tu presencia yo quiero adorar\nEstoy sintiendo tu espíritu en mí\n\n\n\nJesús tú estás aquí\n\nSiento que me lleno de ti\n\nNo quiero parar de adorar\n\nPues me das libertad\n\nJesús tú estás aquí\n\nSiento que me lleno de ti\n\nNo quiero parar de adorar\n\nPues me das libertad\n\nSiento que me lleno de ti\n\nNo quiero parar de adorar\n\nPues me das libertad\n\nJesús tú estás aquí\n\nSiento que me lleno de ti\n\nNo quiero parar de adorar\n\nPues me das libertad\nJesús tú estás aquí\n\n\n\n\n\n\n\nUuoouh, uuoouh, uh, uh, uuuh\n\nUuoouh, uuoouh, uh, uh, uuuh\n\nUuoouh, uuoouh, uh, uh, uuuh\nUuoouh, uuoouh, uh, uh, uuuh\nUuoouh, uuoouh, uh, uh, uuuh\nEstoy sintiendo tu espíritu en mí\n\nSiento correr la unción aquí\n\nMe está tocando tu fuego celestial\n\nY en tu presencia yo quiero adorar\n\nSiento correr la unción aquí\n\nMe está tocando tu fuego celestial\n\nY en tu presencia yo quiero adorar\nEstoy sintiendo tu espíritu en mí\n\n\n\nJesús tú estás aquí\n\nSiento que me lleno de ti\n\nNo quiero parar de adorar\n\nPues me das libertad\n\nJesús tú estás aquí\n\nSiento que me lleno de ti\n\nNo quiero parar de adorar\n\nPues me das libertad\n\nSiento que me lleno de ti\n\nNo quiero parar de adorar\n\nPues me das libertad\n\nJesús tú estás aquí\n\nSiento que me lleno de ti\n\nNo quiero parar de adorar\n\nPues me das libertad\nJesús tú estás aquí\n\n\n\n\n\n\n\nPues me das libertad\n\nPues me das libertad\n\nPues me das libertad\n\n\n\nPues me das libertad\n\nPues me das libertad\n\n\nPues me das libertad"]}