{"title":"Úngeme de Roberto Orellana","slug":"letra-nombre-poderoso-roberto-orellana","author":"Roberto Orellana","album":"Nombre Poderoso","lyrics":"Úngeme, úngeme que yo pueda ver\n\nLo que estás haciendo en mí.\n\n\n\nMi corazón anhela tu presencia \n\nY mi alma de sea tu altar\n\nYo solo quiero recibir un toque tuyo\n\nY que tu unción me pueda transformar.","lyricsStanzas":["Úngeme, úngeme que yo pueda ver\n\nLo que estás haciendo en mí.","Mi corazón anhela tu presencia \n\nY mi alma de sea tu altar\n\nYo solo quiero recibir un toque tuyo\n\nY que tu unción me pueda transformar."]}