{"title":"Como Dios ninguno","slug":"letra-como-dios-ninguno-danilo-ordonez","author":"Danilo Ordoñez","album":"Camino de Valientes","lyrics":"Señor, yo he pensado que la vida sin ti no vale nada\nEl mundo lleno de sin sabores, rodeado en guerras y de maldad\nNiños que lloran en tristes ruinas, la humanidad sufre pidiendo ayuda\nY lo más triste, buscan al hombre y no a Dios\n\nCoro\nSi buscaran a Dios de todo corazón\nYo respondería y calmaría el dolor\nEl hombre gozaría la paz que da Cristo\nY el gozo inefable de la salvación\nEs que vivir con Dios, y gozar de su amor\nEs la vida más linda, mi ser lo experimentó\nEstoy seguro y lo digo que como Dios no hay ninguno\nÉl tiene la paz para el mundo de \nhoy\n\nII\nYo no sé, yo no sé por qué la humanidad sufre y no buscan a Dios,\nLejos de Dios el alma llora sin ninguna esperanza y sin consolación\nEs mejor que le entregues al señor tu vida\nLe dará refrigerio a tu alma angustiada\nY aunque vengan negras y terribles tormentas\nEn los brazos de Cristo seguro estarás\n\nEn los brazos de Cristo seguro estarás\n\nEn los brazos de Cristo seguro estarás","lyricsStanzas":["Señor, yo he pensado que la vida sin ti no vale nada\nEl mundo lleno de sin sabores, rodeado en guerras y de maldad\nNiños que lloran en tristes ruinas, la humanidad sufre pidiendo ayuda\nY lo más triste, buscan al hombre y no a Dios\n\nCoro\nSi buscaran a Dios de todo corazón\nYo respondería y calmaría el dolor\nEl hombre gozaría la paz que da Cristo\nY el gozo inefable de la salvación\nEs que vivir con Dios, y gozar de su amor\nEs la vida más linda, mi ser lo experimentó\nEstoy seguro y lo digo que como Dios no hay ninguno\nÉl tiene la paz para el mundo de \nhoy\n\nII\nYo no sé, yo no sé por qué la humanidad sufre y no buscan a Dios,\nLejos de Dios el alma llora sin ninguna esperanza y sin consolación\nEs mejor que le entregues al señor tu vida\nLe dará refrigerio a tu alma angustiada\nY aunque vengan negras y terribles tormentas\nEn los brazos de Cristo seguro estarás\n\nEn los brazos de Cristo seguro estarás\n\nEn los brazos de Cristo seguro estarás"]}