{"title":"Jesús, amigo fiel","slug":"letra-fiel-amigo-hnos-devia","author":"Hnos Devia","album":"En Ti Está la Vida","lyrics":"Hoy mi Jesús tocando está tu puerta\nNo te detengas, ábrele tu alma\n\nNo te detengas, ábrele tu alma\nNo menosprecies la voz que te llama\n\nNo menosprecies la voz que te llama\nÉl solo quiere darte la calma\n\nÉl solo quiere darte la calma\n\nCoro\n\nCoro\nQuién es aquel que con gran sacrificio\n\nQuién es aquel que con gran sacrificio\nEn una cruz ofreciera su vida\n\nEn una cruz ofreciera su vida\nNo estimo ni su propia existencia\n\nNo estimo ni su propia existencia\nY con su\nmuerte nos brindó la vida Y con su\nmuerte nos brindó la vida\n\nIIII\nOye su voz apacible y hermosa\n\nOye su voz apacible y hermosa\nQue con cariño te está llamando\n\nQue con cariño te está llamando\nCon gran amor él te brinda su mano\n\nCon gran amor él te brinda su mano\nY con dureza tú la rechazas\n\nY con dureza tú la rechazas","lyricsStanzas":["Hoy mi Jesús tocando está tu puerta\nNo te detengas, ábrele tu alma\n\nNo te detengas, ábrele tu alma\nNo menosprecies la voz que te llama\n\nNo menosprecies la voz que te llama\nÉl solo quiere darte la calma\n\nÉl solo quiere darte la calma\n\nCoro\n\nCoro\nQuién es aquel que con gran sacrificio\n\nQuién es aquel que con gran sacrificio\nEn una cruz ofreciera su vida\n\nEn una cruz ofreciera su vida\nNo estimo ni su propia existencia\n\nNo estimo ni su propia existencia\nY con su\nmuerte nos brindó la vida Y con su\nmuerte nos brindó la vida\n\nIIII\nOye su voz apacible y hermosa\n\nOye su voz apacible y hermosa\nQue con cariño te está llamando\n\nQue con cariño te está llamando\nCon gran amor él te brinda su mano\n\nCon gran amor él te brinda su mano\nY con dureza tú la rechazas\n\nY con dureza tú la rechazas"]}