{"title":"Juventud acuérdate de Jehová","slug":"letra-juventud-busca-a-dios-espiritu-vente","author":"Espiritu Vente","album":"15 Grandes Éxitos, Vol. 1","lyrics":"//Esta vida es pasajera,\n\nPeregrina en esta tierra,\n\nComo toda flor del campo\n\nQue mañana se marchita//.\n\n\n\n//Juventud//\n\nAcuérdate de Jehová ahora que eres joven\n\nY dale tu corazón para amarle y adorarle\n\n//Juventud busca a Dios//.\n\n\n\n//Nuestros días son muy cortos,\n\nAños vienen y se vuelan,\n\nUnos nacen y otros mueren,\n\nVanidad de vanidades//.","lyricsStanzas":["//Esta vida es pasajera,\n\nPeregrina en esta tierra,\n\nComo toda flor del campo\n\nQue mañana se marchita//.","//Juventud//\n\nAcuérdate de Jehová ahora que eres joven\n\nY dale tu corazón para amarle y adorarle\n\n//Juventud busca a Dios//.","//Nuestros días son muy cortos,\n\nAños vienen y se vuelan,\n\nUnos nacen y otros mueren,\n\nVanidad de vanidades//."]}