{"title":"El milagro","slug":"letra-el-milagro-fer-ariza","author":"Fer Ariza","album":null,"lyrics":"Oh oh oh el milagro del señor que a todos sorprendió\n\nDios en carne se manifestó, fue Jesús el salvador\n\nQue al mundo liberó, su promesa vida eterna nos dio\n\nCoro\n\nCon campanas y tambores, mucha alegría\n\nPues llegó el Mesías, el redentor\n\nRey de reyes, asombroso, invencible poderoso Dios\n\nCelebremos hoy\n\nIIOh oh oh todo el pueblo de Belén\n\nAdmiró su gran poder… ahora todos adorémosle\n\nFue Jesús el salvador que al mundo liberó\n\nSu promesa vida eterna nos Dios","lyricsStanzas":["Oh oh oh el milagro del señor que a todos sorprendió\n\nDios en carne se manifestó, fue Jesús el salvador\n\nQue al mundo liberó, su promesa vida eterna nos dio\n\nCoro\n\nCon campanas y tambores, mucha alegría\n\nPues llegó el Mesías, el redentor\n\nRey de reyes, asombroso, invencible poderoso Dios\n\nCelebremos hoy\n\nIIOh oh oh todo el pueblo de Belén\n\nAdmiró su gran poder… ahora todos adorémosle\n\nFue Jesús el salvador que al mundo liberó\n\nSu promesa vida eterna nos Dios"]}