{"title":"Contigo viviré y ya nunca sufriré","slug":"letra-contigo-vivere-y-ya-nunca-sufrire-cancion-cristiana","author":"Desconocido","album":null,"lyrics":"A Cristo quiero servirle,\n\nMientras tenga que vivir.\n\nSe tú mi ayudador, Señor\n\nTú eres mi Dios y Salvador.\n\n\n\nContigo viviré, y ya nunca sufriré.\n\nTú eres refugio del pobre,\n\nPor eso a ti alabare.\n\n\n\nTú eres refugio del pobre,\n\nFirme apoyo es tu amor;\n\nPor eso yo a ti alabo, Señor,\n\nPor tu bondad que me salvó.\n\n\n\nPerdido yo me encontraba,\n\nMas tu amor me libertó;\n\nTu muerte en la cruz vida me dio,\n\nAlabaré tu nombre aquí.\n\n\n\nCuando termine la lucha,\n\nA tu lado yo estaré;\n\nContigo viviré y gozaré\n\nDonde tú estás, mi Salvador.","lyricsStanzas":["A Cristo quiero servirle,\n\nMientras tenga que vivir.\n\nSe tú mi ayudador, Señor\n\nTú eres mi Dios y Salvador.","Contigo viviré, y ya nunca sufriré.\n\nTú eres refugio del pobre,\n\nPor eso a ti alabare.","Tú eres refugio del pobre,\n\nFirme apoyo es tu amor;\n\nPor eso yo a ti alabo, Señor,\n\nPor tu bondad que me salvó.","Perdido yo me encontraba,\n\nMas tu amor me libertó;\n\nTu muerte en la cruz vida me dio,\n\nAlabaré tu nombre aquí.","Cuando termine la lucha,\n\nA tu lado yo estaré;\n\nContigo viviré y gozaré\n\nDonde tú estás, mi Salvador."]}