{"title":"Sólo Cristo","slug":"letra-solo-cristo-danilo-ordonez","author":"Danilo Ordoñez","album":"En Oración","lyrics":"Nadie\nte va a amar como Dios te ama\nNadie\nte va a cuidar como Dios te cuida\n\nNadie\nte va a cuidar como Dios te cuida\nNadie\nte acompañará en la soledad\n\nNadie\nte acompañará en la soledad\nCuando\npiensas que estas solo, allí él está\n\nCuando\npiensas que estas solo, allí él está\nÉl te\ndefenderá cuando todos te acusan\n\nÉl te\ndefenderá cuando todos te acusan\nQuién\nte extenderá la mano a punto de desmayar\n\nQuién\nte extenderá la mano a punto de desmayar\nQuién\nquitará el dolor del cuerpo y del alma\n\nQuién\nquitará el dolor del cuerpo y del alma\nQuién\nquitará esa angustia que te hace llorar el alma\n\nQuién\nquitará esa angustia que te hace llorar el alma\n\nCoro\n\nCoro\nSólo cristo,\nsu ternura, su dulzura, su ayuda\n\nSólo cristo,\nsu ternura, su dulzura, su ayuda\nTrae abrigo,\naceite fresco para suavizar\n\nTrae abrigo,\naceite fresco para suavizar\nY quitar\ntoda congoja que atropelle el alma\n\nY quitar\ntoda congoja que atropelle el alma\nY darle\narmonía a tu vida, en su amor renace la esperanza\n\nY darle\narmonía a tu vida, en su amor renace la esperanza\nLo caído\nse levanta y lo perdido se encuentra\n\nLo caído\nse levanta y lo perdido se encuentra\nEl temor\nencuentra calma y la tristeza alegría\n\nEl temor\nencuentra calma y la tristeza alegría\nCuando\nCristo llega al hombre todo, todo le cambia\n\nCuando\nCristo llega al hombre todo, todo le cambia\nY le da\nvida a la vida y el amor se encuentra\n\nY le da\nvida a la vida y el amor se encuentra\n\nIIII\nConfía\nen el señor Jesús que su poder nunca falla\n\nConfía\nen el señor Jesús que su poder nunca falla\nEntrega\ntus pesadas cargas, que él te hará descansar\n\nEntrega\ntus pesadas cargas, que él te hará descansar\nNo dejes\nque tu vida se llene de terror y agonía\n\nNo dejes\nque tu vida se llene de terror y agonía\nEsconde\ntu vida en Cristo, que seguro estarás\n\nEsconde\ntu vida en Cristo, que seguro estarás\nEl que\ncalma las tempestades está aquí, te llama\n\nEl que\ncalma las tempestades está aquí, te llama\nEl que\nsacia el alma sedienta te quiere saciar\n\nEl que\nsacia el alma sedienta te quiere saciar\nEl que\nhace grandes proezas y milagros te busca\n\nEl que\nhace grandes proezas y milagros te busca\nDeja que\nahora tu vida reciba del señor las delicias\n\nDeja que\nahora tu vida reciba del señor las delicias","lyricsStanzas":["Nadie\nte va a amar como Dios te ama\nNadie\nte va a cuidar como Dios te cuida\n\nNadie\nte va a cuidar como Dios te cuida\nNadie\nte acompañará en la soledad\n\nNadie\nte acompañará en la soledad\nCuando\npiensas que estas solo, allí él está\n\nCuando\npiensas que estas solo, allí él está\nÉl te\ndefenderá cuando todos te acusan\n\nÉl te\ndefenderá cuando todos te acusan\nQuién\nte extenderá la mano a punto de desmayar\n\nQuién\nte extenderá la mano a punto de desmayar\nQuién\nquitará el dolor del cuerpo y del alma\n\nQuién\nquitará el dolor del cuerpo y del alma\nQuién\nquitará esa angustia que te hace llorar el alma\n\nQuién\nquitará esa angustia que te hace llorar el alma\n\nCoro\n\nCoro\nSólo cristo,\nsu ternura, su dulzura, su ayuda\n\nSólo cristo,\nsu ternura, su dulzura, su ayuda\nTrae abrigo,\naceite fresco para suavizar\n\nTrae abrigo,\naceite fresco para suavizar\nY quitar\ntoda congoja que atropelle el alma\n\nY quitar\ntoda congoja que atropelle el alma\nY darle\narmonía a tu vida, en su amor renace la esperanza\n\nY darle\narmonía a tu vida, en su amor renace la esperanza\nLo caído\nse levanta y lo perdido se encuentra\n\nLo caído\nse levanta y lo perdido se encuentra\nEl temor\nencuentra calma y la tristeza alegría\n\nEl temor\nencuentra calma y la tristeza alegría\nCuando\nCristo llega al hombre todo, todo le cambia\n\nCuando\nCristo llega al hombre todo, todo le cambia\nY le da\nvida a la vida y el amor se encuentra\n\nY le da\nvida a la vida y el amor se encuentra\n\nIIII\nConfía\nen el señor Jesús que su poder nunca falla\n\nConfía\nen el señor Jesús que su poder nunca falla\nEntrega\ntus pesadas cargas, que él te hará descansar\n\nEntrega\ntus pesadas cargas, que él te hará descansar\nNo dejes\nque tu vida se llene de terror y agonía\n\nNo dejes\nque tu vida se llene de terror y agonía\nEsconde\ntu vida en Cristo, que seguro estarás\n\nEsconde\ntu vida en Cristo, que seguro estarás\nEl que\ncalma las tempestades está aquí, te llama\n\nEl que\ncalma las tempestades está aquí, te llama\nEl que\nsacia el alma sedienta te quiere saciar\n\nEl que\nsacia el alma sedienta te quiere saciar\nEl que\nhace grandes proezas y milagros te busca\n\nEl que\nhace grandes proezas y milagros te busca\nDeja que\nahora tu vida reciba del señor las delicias\n\nDeja que\nahora tu vida reciba del señor las delicias"]}