{"title":"La iglesia del Señor","post_title":"Letra y Significado de La iglesia del Señor - Canción Cristiana","slug":"letra-la-iglesia-del-senor-cancion-cristiana","meta_description":"Explora la letra y el significado de La iglesia del Señor, una canción cristiana de adoración. Reflexiona sobre su mensaje espiritual y devocional.","author":"Desconocido","lyrics":["//La iglesia del Señor se tiene que mover,\n\nCon el poder de Cristo para poder vencer//.","//Levanto mis manos para pedir poder,\n\nPorque soy cristiano, y quiero vencer//."],"youtube_id":"","album":"","content":"<h2>La iglesia del Señor - Letra y Significado</h2><p><strong>La iglesia del Señor</strong> es una <em>canción cristiana</em> de adoración que ha resonado en congregaciones y grupos de alabanza. Aunque el autor es desconocido, su mensaje sigue vigente, inspirando a quienes buscan fortalecer su fe y vivir en victoria. Esta melodía es interpretada en diversos contextos, siendo parte esencial de la música de adoración en la comunidad cristiana.</p><h3>Significado de la letra de La iglesia del Señor</h3><p>La letra de <strong>La iglesia del Señor</strong> invita a los creyentes a moverse con el poder de Cristo, recordando que la victoria espiritual es posible a través de la fe. El mensaje central es la dependencia del poder divino para vencer las dificultades y tentaciones. El autor transmite la importancia de la oración y la entrega total a Dios, motivando a levantar las manos y pedir fortaleza.</p><blockquote>La iglesia del Señor se tiene que mover, con el poder de Cristo para poder vencer.</blockquote><p>Este fragmento resalta la necesidad de acción y confianza en el Señor, elementos fundamentales en la vida cristiana.</p><h3>Mensaje espiritual y devocional</h3><p>La canción enfatiza el llamado a vivir como verdaderos cristianos, buscando el poder de Dios para superar los retos diarios. Es un himno que anima a la comunidad a permanecer firme en la fe, recordando que la victoria viene de Cristo. La música de adoración como <strong>La iglesia del Señor</strong> fortalece el espíritu y une a los creyentes en un propósito común.</p><blockquote>Levanto mis manos para pedir poder, porque soy cristiano, y quiero vencer.</blockquote><p>Este verso refleja el deseo de cada creyente de recibir poder y vencer, una oración que se repite en muchos corazones.</p><h3>Sobre el autor y contexto musical</h3><p>El autor de <strong>La iglesia del Señor</strong> es desconocido, pero la canción ha sido adoptada por diversas iglesias y ministerios de música cristiana. Su sencillez y profundidad la convierten en una pieza clave para la adoración congregacional. Aunque no se conoce el álbum original, su popularidad demuestra el impacto de la música de adoración en la vida espiritual.</p><p>En conclusión, <strong>La iglesia del Señor</strong> es una canción cristiana que motiva a la iglesia a buscar el poder de Cristo y vivir en victoria. Que su mensaje inspire a cada creyente a levantar sus manos y confiar plenamente en el Señor.</p>","generated_at":"2026-02-11T23:24:26.871Z"}