{"title":"Adelante juventud","post_title":"Letra de Adelante Juventud - Desconocido | Significado y Reflexión","slug":"letra-adelante-juventud-desconocido","meta_description":"Conoce la letra y el significado de Adelante Juventud del álbum Ayuda a tu Siervo. Reflexiona sobre esta canción cristiana de adoración y fe.","author":"Desconocido","lyrics":["//Adelante juventud, sin temor, con valor,\n\nNo vayáis a olvidar el poder de Jesús//.","//Acordaos de Israel cuando preso se encontró\n\nY Moisés los libertó con el gran poder de Dios//."],"youtube_id":"","album":"Ayuda a tu Siervo","content":"<h2>Adelante Juventud - Letra y Significado de la Canción Cristiana</h2><p><strong>Adelante Juventud</strong> es una <em>canción cristiana</em> incluida en el álbum <strong>Ayuda a tu Siervo</strong>. Aunque el autor y artista son desconocidos, esta melodía ha impactado a muchas congregaciones por su mensaje de ánimo y fe. Es una pieza de <strong>música de adoración</strong> que motiva a la juventud a confiar en el poder de Jesús.</p><h3>Significado de la Letra de Adelante Juventud</h3><p>La <strong>letra de Adelante Juventud</strong> invita a los jóvenes a avanzar con valor, recordando el poder de Jesús en sus vidas. El mensaje central es la confianza en Dios, incluso en momentos de dificultad. El autor utiliza la historia de Israel y Moisés como ejemplo de cómo Dios puede liberar y transformar situaciones imposibles.</p><blockquote>Adelante juventud, sin temor, con valor,<br>No vayáis a olvidar el poder de Jesús.</blockquote><p>Esta cita resalta la importancia de no olvidar la fuerza espiritual que proviene de Cristo, animando a la juventud a mantenerse firme en la fe.</p><h3>Mensaje Espiritual y Reflexión Cristiana</h3><p>La canción destaca el poder de Dios para liberar y guiar a su pueblo, como lo hizo con Israel a través de Moisés. Es un llamado a la perseverancia y a la confianza en el Señor, especialmente para quienes enfrentan desafíos. <em>Adelante Juventud</em> es un himno de esperanza y fortaleza espiritual.</p><h3>Sobre el Álbum Ayuda a tu Siervo</h3><p><strong>Ayuda a tu Siervo</strong> es un álbum que reúne canciones de adoración y alabanza, enfocadas en fortalecer la fe y el compromiso cristiano. Aunque no se conoce el artista, el álbum ha sido utilizado en diversas comunidades para inspirar y motivar a los creyentes.</p><p>En conclusión, <strong>Adelante Juventud</strong> es una <em>canción cristiana</em> que anima a la juventud a confiar en el poder de Jesús. Su mensaje devocional invita a recordar que, como Moisés y el pueblo de Israel, podemos superar cualquier obstáculo con la ayuda de Dios. Que esta canción sea un recordatorio de fe y esperanza en tu caminar espiritual.</p>","generated_at":"2026-02-11T23:41:45.568Z"}