{
  "title": "Alegre los niñitos",
  "post_title": "Letra y Significado de Alegre los niñitos - Canción Cristiana",
  "slug": "letra-alegre-los-ninitos-cancion-cristiana",
  "meta_description": "Descubre la letra y el significado de Alegre los niñitos, una canción cristiana de adoración para niños. Reflexiona sobre su mensaje espiritual.",
  "author": "Desconocido",
  "lyrics": [
    "Alegre los niñitos\n\nAlegre los niñitos.",
    "//No habrá tristeza, no habrá dolor\n\nPara los niñitos que alaban al Señor//."
  ],
  "youtube_id": "",
  "album": "",
  "content": "<h2>Letra de Alegre los niñitos - Canción Cristiana</h2><p><strong>Alegre los niñitos</strong> es una <em>canción cristiana</em> tradicional que ha acompañado a generaciones de niños en momentos de adoración y alabanza. Aunque el <strong>autor</strong> es desconocido, su mensaje sigue vigente en la comunidad cristiana, especialmente en encuentros infantiles y escuelas dominicales.</p><h3>Significado de la Letra de Alegre los niñitos</h3><p>La <strong>letra de Alegre los niñitos</strong> transmite esperanza y alegría, recordando que en la presencia del Señor no hay tristeza ni dolor. Este mensaje es fundamental en la <em>música de adoración</em> para niños, pues invita a los pequeños a acercarse a Dios con confianza y gozo.</p><blockquote>No habrá tristeza, no habrá dolor<br>Para los niñitos que alaban al Señor.</blockquote><p>El autor quiso resaltar la importancia de la alabanza en la vida de los niños, mostrando que el amor de Dios transforma cualquier situación y llena de paz el corazón.</p><h3>Mensaje Espiritual en la Canción Cristiana</h3><p>Esta <strong>canción cristiana</strong> es ideal para enseñar a los niños sobre la bondad y el consuelo que ofrece el Señor. Al cantar <em>Alegre los niñitos</em>, se refuerza la idea de que la adoración es una fuente de alegría y fortaleza espiritual.</p><h3>Sobre el Autor y Contexto</h3><p>El <strong>autor</strong> de <em>Alegre los niñitos</em> es desconocido, pero la canción ha sido interpretada en diversos contextos cristianos, formando parte de repertorios de <strong>música de adoración</strong> infantil. Su sencillez y profundidad la hacen relevante en la enseñanza bíblica.</p><p>En conclusión, <strong>Alegre los niñitos</strong> es una invitación a vivir la fe con alegría y confianza. Que cada niño que la cante experimente el amor y la paz que solo Dios puede dar. Reflexionemos sobre cómo la <em>adoración</em> transforma nuestras vidas y nos acerca más al Señor.</p>",
  "generated_at": "2026-02-12T01:40:40.846Z"
}