{"title":"Una sola puerta","post_title":"Letra de Una Sola Puerta - Canción Cristiana | Significado y Reflexión","slug":"letra-una-sola-puerta-cancion-cristiana","meta_description":"Descubre la letra y el significado de Una Sola Puerta, canción cristiana del álbum No Busques Mas. Reflexiona sobre su mensaje espiritual.","author":"Desconocido","lyrics":["Una sola puerta hay\n\nMas son sus lados dos\n\nAdentro y afuera y tu\n\n¿Dónde estás?","Una sola puerta hay\n\nMas son sus lados dos\n\n//Yo estoy adentro y tu\n\n¿Dónde estás?\n\n¡Adentro! //"],"youtube_id":"","album":"No Busques Mas","content":"<h2>Letra de Una Sola Puerta – Canción Cristiana</h2><p><strong>Una Sola Puerta</strong> es una <em>canción cristiana</em> incluida en el álbum <strong>No Busques Mas</strong>. Aunque el autor es desconocido, esta alabanza ha tocado el corazón de muchos creyentes por su mensaje profundo y sencillo. Es una pieza muy apreciada en reuniones de <strong>música de adoración</strong> y momentos devocionales, invitando a la reflexión sobre nuestra posición espiritual ante Dios.</p><h3>Significado de la letra de Una Sola Puerta</h3><p>La <strong>letra de Una Sola Puerta</strong> utiliza la imagen de una puerta con dos lados para ilustrar una verdad espiritual: todos debemos decidir si estamos “adentro” o “afuera” del Reino de Dios. El mensaje central es la invitación a entrar y permanecer en la presencia de Cristo, quien es la única puerta hacia la salvación.</p><blockquote>“Una sola puerta hay, mas son sus lados dos. Adentro y afuera y tú, ¿dónde estás?”</blockquote><p>Esta pregunta directa nos lleva a examinar nuestro corazón y nuestra relación con Dios. La canción nos recuerda que la decisión de entrar es personal y urgente.</p><h3>Mensaje espiritual y reflexión cristiana</h3><p>El mensaje espiritual de <strong>Una Sola Puerta</strong> es claro: Jesús es la única puerta (Juan 10:9) y cada persona debe decidir si acepta su invitación. La canción es ideal para momentos de <em>adoración</em> y llamados a la reflexión, ya que confronta suavemente al oyente sobre su posición espiritual.</p><blockquote>“Yo estoy adentro y tú, ¡adentro!”</blockquote><p>Este fragmento expresa el deseo de compartir la fe y animar a otros a entrar en la vida nueva que Cristo ofrece.</p><h3>Sobre el álbum No Busques Mas</h3><p>El álbum <strong>No Busques Mas</strong> reúne varias canciones cristianas que invitan a buscar a Dios como la única fuente de vida y esperanza. <strong>Una Sola Puerta</strong> destaca por su mensaje sencillo y directo, ideal para la enseñanza y la meditación en la comunidad cristiana.</p><p>En conclusión, <em>Una Sola Puerta</em> es una <strong>canción cristiana</strong> que nos desafía a tomar una decisión espiritual importante. Que su mensaje nos inspire a permanecer “adentro”, en comunión con Dios, y a invitar a otros a cruzar esa puerta de fe y salvación.</p>","generated_at":"2026-02-12T12:25:54.590Z"}