{
  "name": "Hector David",
  "slug": "hector-david",
  "songCount": 1,
  "thumbnailUrl": "https://i.ytimg.com/vi/hNSWe-K9koE/hqdefault.jpg",
  "songs": [
    {
      "slug": "letra-en-el-principio-hector-david",
      "title": "En el Principio",
      "author": "Hector David",
      "album": "Israel 2",
      "metaDescription": "Descubre la letra de En El Principio de Hector David, su significado y mensaje espiritual. Una canción cristiana de adoración del álbum Israel 2.",
      "lyricsPreview": "En el principio el espíritu de Dios - Coros de Alabanza En el principio el espíritu de Dios - Coros de Alabanza En el principio el espíritu de Dios, Se movía sobre las aguas,Se mo...",
      "youtubeId": "hNSWe-K9koE",
      "thumbnailUrl": "https://i.ytimg.com/vi/hNSWe-K9koE/hqdefault.jpg",
      "generatedAt": "2026-02-12T16:33:10.891Z"
    }
  ]
}