{
  "name": "Juan Luis Guerra 4.40",
  "slug": "juan-luis-guerra-4-40",
  "songCount": 1,
  "thumbnailUrl": "https://i.ytimg.com/vi/BK4LViHwV7g/hqdefault.jpg",
  "songs": [
    {
      "slug": "letra-son-al-rey-juan-luis-guerra",
      "title": "Son al rey de Juan Luis Guerra",
      "author": "Juan Luis Guerra 4.40",
      "album": "Asondeguerra",
      "metaDescription": "Descubre la letra y el significado de Son Al Rey de Juan Luis Guerra. Reflexiona sobre esta canción cristiana de adoración y su mensaje espiritual.",
      "lyricsPreview": "Majestuoso y poderoso (poderoso) Admirable y siempre digno (siempre digno) Exaltado sea tu nombre Por los siglos de los siglos. Tú pagaste por mi vida (por mi vida) Te ofreciste e...",
      "youtubeId": "BK4LViHwV7g",
      "thumbnailUrl": "https://i.ytimg.com/vi/BK4LViHwV7g/hqdefault.jpg",
      "generatedAt": "2026-02-12T14:25:03.873Z"
    }
  ]
}