{
  "name": "Mensajeros Del Calvario",
  "slug": "mensajeros-del-calvario",
  "songCount": 1,
  "thumbnailUrl": null,
  "songs": [
    {
      "slug": "letra-ven-a-jesus-mensajeros-del-calvario",
      "title": "Ven a Jesús de Mensajeros del Calvario",
      "author": "Mensajeros Del Calvario",
      "album": null,
      "metaDescription": "Descubre la letra y el significado de Ven a Jesús de Mensajeros del Calvario. Reflexiona sobre esta canción cristiana de adoración y su mensaje espiritual.",
      "lyricsPreview": "Noble invitación de Cristo amado A todos los perdidos y sin fe Que llevan en su espalda los pecados Y que siguen como el ciego que no ve Benignos que hacen tu deidad Yo sé que te...",
      "youtubeId": null,
      "thumbnailUrl": null,
      "generatedAt": "2026-02-12T13:34:37.989Z"
    }
  ]
}