{
  "name": "tony feliz",
  "slug": "tony-feliz",
  "songCount": 1,
  "thumbnailUrl": "https://i.ytimg.com/vi/9R9hhkR5Foo/hqdefault.jpg",
  "songs": [
    {
      "slug": "letra-sin-santidad-alabnzaen-blues-cristina",
      "title": "Sin santidad",
      "author": "Alabnzaen blues cristina, alabaza.en.bluesf, tony feliz",
      "album": "Sin Santidad",
      "metaDescription": "Explora la letra y el significado de Sin Santidad de Alabnzaen blues cristina. Reflexiona sobre este mensaje de música de adoración cristiana.",
      "lyricsPreview": "//Sin santidad nadie verá al Señor// //Pero yo sé// //Que le veré// Y con su espíritu me santificaré.",
      "youtubeId": "9R9hhkR5Foo",
      "thumbnailUrl": "https://i.ytimg.com/vi/9R9hhkR5Foo/hqdefault.jpg",
      "generatedAt": "2026-02-11T23:17:03.715Z"
    }
  ]
}